{"inkVersion":20,"root":[["^Juan: ¡Uf hace mucho calor!","\n","ev","str","^¡Sí!","/str","/ev",{"*":"0.c-0","flg":20},"ev","str","^¡Adiós!","/str","/ev",{"*":"0.c-1","flg":20},{"c-0":["^ Player: ¡Sí, demasiado!","\n","^Juan: ¡Apenas ir por unas Tecates al Ancira! ¡Bien heladas!","\n",[{"*":".^.c-0","flg":24},{"c-0":[{"->":"Divert1"},"\n",{"->":"0.g-0"},{"#f":5}]}],{"#f":5}],"c-1":["^ Player: Este... sí, más o menos. ¡Adiós!","\n",["ev","str","^Continuar","/str","/ev",{"*":".^.c-0","flg":20},{"c-0":["^ ",{"->":"EndPart"},"\n",{"->":"0.g-0"},{"#f":5}]}],{"#f":5}],"g-0":["done",{"#f":5}]}],"done",{"Divert1":[["ev","str","^Horarios","/str","/ev",{"*":".^.c-0","flg":20},"ev","str","^Ubicación","/str","/ev",{"*":".^.c-1","flg":20},"ev","str","^¡Gracias!","/str","/ev",{"*":".^.c-2","flg":20},{"c-0":["^ Player: ¿Estará abierto?","\n","^Juan: Sí, cierran hasta las 10pm. ",{"->":".^.^.^"},"\n",{"#f":5}],"c-1":["^ Player: ¿Dónde lo puedo encontrar?","\n","^Juan: Un poco más adelante, en la esquina de Padre Mier y Juárez. ",{"->":".^.^.^"},"\n",{"#f":5}],"c-2":["^ ¡Gracias por la idea! ",{"->":"EndPart"},"\n",{"#f":5}]}],{"#f":1}],"EndPart":["end",{"#f":1}],"#f":1}],"listDefs":{}}