{"inkVersion":21,"root":[["^Melchor: No te puedo dejar pasar si no conoces... ¡¡¡LOS COLORES!!!","\n","ev","str","^Rojo","/str","/ev",{"*":"0.c-0","flg":20},"ev","str","^Azul","/str","/ev",{"*":"0.c-1","flg":20},"ev","str","^Verde","/str","/ev",{"*":"0.c-2","flg":20},"ev","str","^Amarillo","/str","/ev",{"*":"0.c-3","flg":20},{"c-0":["^ Melchor: Sí... ¿y después?",{"->":"Divert1"},"\n",{"->":"0.g-0"},{"#f":5}],"c-1":["^ ",{"->":"Divert5"},"\n",{"->":"0.g-0"},{"#f":5}],"c-2":["^ ",{"->":"Divert5"},"\n",{"->":"0.g-0"},{"#f":5}],"c-3":["^ ",{"->":"Divert5"},"\n",{"->":"0.g-0"},{"#f":5}],"g-0":["done",{"#f":5}]}],"done",{"Divert1":[["ev","str","^Rojo","/str","/ev",{"*":".^.c-0","flg":20},"ev","str","^Azul","/str","/ev",{"*":".^.c-1","flg":20},"ev","str","^Verde","/str","/ev",{"*":".^.c-2","flg":20},"ev","str","^Amarillo","/str","/ev",{"*":".^.c-3","flg":20},{"c-0":["^ ",{"->":"Divert5"},"\n",{"#f":5}],"c-1":["^ ",{"->":"Divert5"},"\n",{"#f":5}],"c-2":["^ Melchor: SÍ... ¿Y DESPUÉS?",{"->":"Divert2"},"\n",{"#f":5}],"c-3":["^ ",{"->":"Divert5"},"\n",{"#f":5}]}],{"#f":1}],"Divert2":[["ev","str","^Rojo","/str","/ev",{"*":".^.c-0","flg":20},"ev","str","^Azul","/str","/ev",{"*":".^.c-1","flg":20},"ev","str","^Verde","/str","/ev",{"*":".^.c-2","flg":20},"ev","str","^Amarillo","/str","/ev",{"*":".^.c-3","flg":20},{"c-0":["^ ",{"->":"Divert5"},"\n",{"#f":5}],"c-1":["^ ",{"->":"Divert5"},"\n",{"#f":5}],"c-2":["^ ",{"->":"Divert5"},"\n",{"#f":5}],"c-3":["^ Melchor: ¡SÍ! ¿¿¿Y DESPUÉS???",{"->":"Divert3"},"\n",{"#f":5}]}],{"#f":1}],"Divert3":[["ev","str","^Rojo","/str","/ev",{"*":".^.c-0","flg":20},"ev","str","^Azul","/str","/ev",{"*":".^.c-1","flg":20},"ev","str","^Verde","/str","/ev",{"*":".^.c-2","flg":20},"ev","str","^Amarillo","/str","/ev",{"*":".^.c-3","flg":20},{"c-0":["^ ",{"->":"Divert5"},"\n",{"#f":5}],"c-1":["^ Melchor: ¡¡¡SÍÍÍ!!! ",{"->":"Divert4"},"\n",{"#f":5}],"c-2":["^ ",{"->":"Divert5"},"\n",{"#f":5}],"c-3":["^ ",{"->":"Divert5"},"\n",{"#f":5}]}],{"#f":1}],"Divert4":["^¡TÚ SÍ QUE CONOCES LOS COLORES! ¡ADELANTE, PUEDES PASAR!","\n","end",{"#f":1}],"Divert5":["^Melchor: No conoces los colores. Qué lástima.","\n","end",{"#f":1}],"#f":1}],"listDefs":{}}